board_to_fen/.DS_Store
board_to_fen/KerasNeuralNetwork.py
board_to_fen/__init__.py
board_to_fen/predict.py
board_to_fen/test_image.jpeg
board_to_fen/train_model.py
board_to_fen/utils.py
board_to_fen/__pycache__/KerasNeuralNetwork.cpython-37.pyc
board_to_fen/__pycache__/__init__.cpython-37.pyc
board_to_fen/__pycache__/predict.cpython-37.pyc
board_to_fen/__pycache__/utils.cpython-37.pyc
board_to_fen/saved_models/__init__.py
board_to_fen/saved_models/november_model
board_to_fen/saved_models/november_model_weights.h5
board_to_fen/saved_models/__pycache__/__init__.cpython-37.pyc
board_to_fen-0.0.14.dist-info/LICENSE
board_to_fen-0.0.14.dist-info/METADATA
board_to_fen-0.0.14.dist-info/WHEEL
board_to_fen-0.0.14.dist-info/top_level.txt
board_to_fen-0.0.14.dist-info/RECORD
